odoo/addons/ssi_voucher_settlement_common/README.rst
odoo/addons/ssi_voucher_settlement_common/__init__.py
odoo/addons/ssi_voucher_settlement_common/__manifest__.py
odoo/addons/ssi_voucher_settlement_common/static/description/icon.png
odoo/addons/ssi_voucher_settlement_common/views/mixin_account_voucher_views.xml
odoo14_addon_ssi_voucher_settlement_common-14.0.1.3.3.dist-info/METADATA
odoo14_addon_ssi_voucher_settlement_common-14.0.1.3.3.dist-info/WHEEL
odoo14_addon_ssi_voucher_settlement_common-14.0.1.3.3.dist-info/top_level.txt
odoo14_addon_ssi_voucher_settlement_common-14.0.1.3.3.dist-info/RECORD
